llm_utility_pack-4.3.dist-info/licenses/LICENSE
tests/__init__.py
tests/test_decorators.py
tests/test_duck_vector_database.py
tests/test_embeddings.py
tests/test_extraction.py
tests/test_llm.py
tests/test_lmdb_vdb_mongo_ops.py
tests/test_logger.py
tests/test_memory.py
tests/test_parallel.py
tests/test_parsers.py
tests/test_rotational_quantization.py
tests/test_text.py
tests/test_vector_database_all_modes.py
utility_pack/__init__.py
utility_pack/decorators.py
utility_pack/embeddings.py
utility_pack/extraction.py
utility_pack/fastapi_wrapper.py
utility_pack/llm.py
utility_pack/logger.py
utility_pack/memory.py
utility_pack/ml.py
utility_pack/ocr_util.py
utility_pack/parallel.py
utility_pack/parsers.py
utility_pack/pdfs.py
utility_pack/rotational_quantization.py
utility_pack/text.py
utility_pack/vector_cache.py
utility_pack/vector_storage.py
utility_pack/vector_storage_helper.py
utility_pack/resources/en_stopwords.pkl
utility_pack/resources/lid.176.ftz
utility_pack/resources/pt_stopwords.pkl
utility_pack/resources/embedding-model/universal_sentence_encoder_quantized.onnx
utility_pack/resources/question-classifier/model.onnx
utility_pack/resources/question-classifier/tokenizer.json
utility_pack/resources/reranker/model.onnx
utility_pack/resources/reranker/tokenizer.json
llm_utility_pack-4.3.dist-info/METADATA
llm_utility_pack-4.3.dist-info/WHEEL
llm_utility_pack-4.3.dist-info/top_level.txt
llm_utility_pack-4.3.dist-info/RECORD
