Metadata-Version: 2.4
Name: llm_utility_pack
Version: 4.3
Author: Carlo Moro
Author-email: Carlo Moro <cnmoro@gmail.com>
Classifier: Programming Language :: Python :: 3
Classifier: License :: OSI Approved :: MIT License
Classifier: Operating System :: OS Independent
Requires-Python: >=3.7
License-File: LICENSE
Requires-Dist: cloudpickle
Requires-Dist: pytz
Requires-Dist: ollama
Requires-Dist: requests
Requires-Dist: aiohttp
Requires-Dist: asyncio
Requires-Dist: lmdb
Requires-Dist: markdown
Requires-Dist: lingua-language-detector
Requires-Dist: deskew
Requires-Dist: semantic-compressor>=2.43
Requires-Dist: PyMuPDF
Requires-Dist: pytesseract
Requires-Dist: opencv-python-headless
Requires-Dist: scikit-image
Requires-Dist: Pillow
Requires-Dist: pandas
Requires-Dist: scikit-learn
Requires-Dist: faiss-cpu
Requires-Dist: numpy
Requires-Dist: thefuzz[speedup]
Requires-Dist: strive-ranker>=2.42
Requires-Dist: shortuuid
Requires-Dist: prophet
Requires-Dist: prince
Requires-Dist: scipy
Requires-Dist: onnxruntime
Requires-Dist: tokenizers
Requires-Dist: tqdm
Requires-Dist: chonkie
Requires-Dist: pymongo
Requires-Dist: openai
Requires-Dist: tiktoken
Requires-Dist: onnxruntime_extensions
Requires-Dist: xxhash
Requires-Dist: fastapi
Requires-Dist: APScheduler
Requires-Dist: uvicorn
Requires-Dist: pydantic
Requires-Dist: sqlalchemy
Requires-Dist: orjson
Requires-Dist: duckdb
Requires-Dist: lightning-disk-kv>=1.1.1
Dynamic: author
Dynamic: license-file
Dynamic: requires-python
